cooker/cooker-menu-schema.json
cooker/cooker.py
yocto_cooker-1.4.0.dist-info/LICENSE
yocto_cooker-1.4.0.dist-info/METADATA
yocto_cooker-1.4.0.dist-info/WHEEL
yocto_cooker-1.4.0.dist-info/entry_points.txt
yocto_cooker-1.4.0.dist-info/top_level.txt
yocto_cooker-1.4.0.dist-info/RECORD
