Metadata-Version: 2.1
Name: yocto-cooker
Version: 1.4.0
Summary: meta build tool for Yocto Project based Linux embedded systems
Home-page: https://github.com/cpb-/yocto-cooker
Author: Christophe BLAESS, Patrick BOETTCHER
Author-email: christophe.blaess@logilin.fr, p@yai.se
License: GPL
Project-URL: Bug Reports, https://github.com/cpb-/yocto-cooker/issues
Project-URL: Source, https://github.com/cpb-/yocto-cooker
Platform: UNKNOWN
License-File: LICENSE
Requires-Dist: jsonschema (>=3.2.0)
Requires-Dist: pyjson5 (>=1.6.2)
Requires-Dist: urllib3 (>=1.22)
